Tutorials/__init__.py
Tutorials/automated_fitting.py
extrack/__init__.py
extrack/auto_fitting.py
extrack/exporters.py
extrack/histograms.py
extrack/readers.py
extrack/refined_localization.py
extrack/simulate_tracks.py
extrack/tracking.py
extrack/tracking_0.py
extrack/version.py
extrack/visualization.py
extrack-1.6.3.dist-info/licenses/LICENSE
extrack-1.6.3.dist-info/METADATA
extrack-1.6.3.dist-info/WHEEL
extrack-1.6.3.dist-info/top_level.txt
extrack-1.6.3.dist-info/RECORD
