Metadata-Version: 2.4
Name: extrack
Version: 1.6.3
Summary: SPT kinetic modelling and states annotation of tracks
Home-page: https://github.com/FrancoisSimon/ExTrack-python3
Author: Francois Simon
Author-email: simon.francois@protonmail.com
Project-URL: Bug Tracker, https://github.com/FrancoisSimon/ExTrack-python3
Classifier: Programming Language :: Python :: 3
Classifier: License :: OSI Approved :: MIT License
Classifier: Operating System :: OS Independent
Classifier: Intended Audience :: Science/Research
Classifier: Development Status :: 3 - Alpha
Requires-Python: >=3.6
License-File: LICENSE
Requires-Dist: lmfit
Requires-Dist: xmltodict
Requires-Dist: pandas
Requires-Dist: matplotlib
Dynamic: author
Dynamic: author-email
Dynamic: classifier
Dynamic: description
Dynamic: description-content-type
Dynamic: home-page
Dynamic: license-file
Dynamic: project-url
Dynamic: requires-dist
Dynamic: requires-python
Dynamic: summary
